katara/__init__.py
katara/audio_utils.py
katara/data_utils.py
katara/image_utils.py
katara/random_utils.py
katara/train_utils.py
katara-0.0.3.dist-info/METADATA
katara-0.0.3.dist-info/WHEEL
katara-0.0.3.dist-info/licenses/LICENSE
katara-0.0.3.dist-info/RECORD
